budosystems/xtra/pytest_suite/__init__.py
budosystems/xtra/pytest_suite/_version.py
budosystems/xtra/pytest_suite/py.typed
budosystems/xtra/pytest_suite/repository/__init__.py
budosystems/xtra/pytest_suite/repository/abstract_test_repository.py
budosystems/xtra/pytest_suite/repository/conftest.py
pytest_budosystems-0.3.0.dist-info/LICENCE.txt
pytest_budosystems-0.3.0.dist-info/METADATA
pytest_budosystems-0.3.0.dist-info/WHEEL
pytest_budosystems-0.3.0.dist-info/entry_points.txt
pytest_budosystems-0.3.0.dist-info/top_level.txt
pytest_budosystems-0.3.0.dist-info/RECORD
