Metadata-Version: 2.1
Name: pytest-budosystems
Version: 0.3.0
Summary: Budo Systems is a martial arts school management system. This module is the Budo Systems Pytest Plugin.
Author-email: Joël Larose <joel.larose@budo.systems>
Project-URL: Repository, https://gitlab.com/budosystems/pytest-budosystems
Project-URL: Issue Tracker, https://gitlab.com/budosystems/pytest-budosystems/-/issues
Keywords: Budo Systems,test,pytest
Classifier: Development Status :: 3 - Alpha
Classifier: License :: OSI Approved :: Apache Software License
Classifier: Operating System :: OS Independent
Classifier: Programming Language :: Python :: 3
Classifier: Programming Language :: Python :: 3.9
Classifier: Programming Language :: Python :: 3.10
Classifier: Framework :: Pytest
Classifier: Topic :: Software Development :: Testing
Classifier: Topic :: Software Development :: Testing :: Unit
Classifier: Typing :: Typed
Requires-Python: >=3.9
License-File: LICENCE.txt
Requires-Dist: budosystems-core
Requires-Dist: pytest
Provides-Extra: all
Requires-Dist: pytest-budosystems[docs,lintcheck,test,typecheck] ; extra == 'all'
Provides-Extra: docs
Requires-Dist: Sphinx ; extra == 'docs'
Requires-Dist: sphinx-git ; extra == 'docs'
Provides-Extra: lintcheck
Requires-Dist: pylint ; extra == 'lintcheck'
Requires-Dist: pylint-venv ; extra == 'lintcheck'
Requires-Dist: pylint-pytest ; extra == 'lintcheck'
Provides-Extra: test
Requires-Dist: pytest-cov ; extra == 'test'
Provides-Extra: typecheck
Requires-Dist: mypy ; extra == 'typecheck'
